fast_cache_middleware/__init__.py
fast_cache_middleware/_helpers.py
fast_cache_middleware/controller.py
fast_cache_middleware/depends.py
fast_cache_middleware/exceptions.py
fast_cache_middleware/middleware.py
fast_cache_middleware/schemas.py
fast_cache_middleware/serializers.py
fast_cache_middleware/storages/__init__.py
fast_cache_middleware/storages/base_storage.py
fast_cache_middleware/storages/in_memory_storage.py
fast_cache_middleware/storages/redis_storage.py
fast_cache_middleware-0.0.7.dist-info/LICENSE
fast_cache_middleware-0.0.7.dist-info/METADATA
fast_cache_middleware-0.0.7.dist-info/WHEEL
fast_cache_middleware-0.0.7.dist-info/RECORD
