Metadata-Version: 2.3
Name: fast-cache-middleware
Version: 0.0.7
Summary: An intelligent middleware for caching FastAPI responses
License: MIT
Author: www.chud0@gmail.com
Requires-Python: >=3.11,<4.0
Classifier: License :: OSI Approved :: MIT License
Classifier: Programming Language :: Python :: 3
Classifier: Programming Language :: Python :: 3.11
Classifier: Programming Language :: Python :: 3.12
Classifier: Programming Language :: Python :: 3.13
Provides-Extra: redis
Requires-Dist: fastapi (>=0.111.1,<1.0.0)
Requires-Dist: pydantic (>=1.7.4,!=1.8,!=1.8.1,!=2.0.0,!=2.0.1,!=2.1.0,<3.0.0)
Requires-Dist: redis (>=6.4.0,<7.0.0) ; extra == "redis"
